[
    {
        "Date": "2026-04-24",
        "Home": "HOU",
        "Away": "LAL",
        "Pred_Home": 124.1,
        "Pred_Away": 125.7,
        "Pred_Total": 249.8,
        "Pred_Spread": 1.6,
        "Actual_Home": 108.0,
        "Actual_Away": 112.0,
        "ML_Hit": 1.0,
        "Spread_Hit": null,
        "Total_Hit": null,
        "Q1_Hit": 0.0,
        "Q2_Hit": 0.0,
        "1H_Hit": 0.0,
        "Pred_Q1_Winner": "Rockets",
        "Pred_Q2_Winner": "Rockets",
        "Pred_1H_Winner": "Lakers"
    },
    {
        "Date": "2026-04-24",
        "Home": "POR",
        "Away": "SA",
        "Pred_Home": 116.2,
        "Pred_Away": 109.3,
        "Pred_Total": 225.5,
        "Pred_Spread": -6.9,
        "Actual_Home": 108.0,
        "Actual_Away": 120.0,
        "ML_Hit": 0.0,
        "Spread_Hit": null,
        "Total_Hit": null,
        "Q1_Hit": 0.0,
        "Q2_Hit": 0.0,
        "1H_Hit": 0.0,
        "Pred_Q1_Winner": "Blazers",
        "Pred_Q2_Winner": "Blazers",
        "Pred_1H_Winner": "Blazers"
    },
    {
        "Date": "2026-04-25",
        "Home": "ORL",
        "Away": "DET",
        "Pred_Home": 117.2,
        "Pred_Away": 118.8,
        "Pred_Total": 236.0,
        "Pred_Spread": 1.6,
        "Actual_Home": 113.0,
        "Actual_Away": 105.0,
        "ML_Hit": 0.0,
        "Spread_Hit": null,
        "Total_Hit": null,
        "Q1_Hit": 0.0,
        "Q2_Hit": 0.0,
        "1H_Hit": 0.0,
        "Pred_Q1_Winner": "Pistons",
        "Pred_Q2_Winner": "Magic",
        "Pred_1H_Winner": "Pistons"
    },
    {
        "Date": "2026-04-25",
        "Home": "PHX",
        "Away": "OKC",
        "Pred_Home": 116.8,
        "Pred_Away": 122.8,
        "Pred_Total": 239.6,
        "Pred_Spread": 6.0,
        "Actual_Home": 109.0,
        "Actual_Away": 121.0,
        "ML_Hit": 1.0,
        "Spread_Hit": null,
        "Total_Hit": null,
        "Q1_Hit": 0.0,
        "Q2_Hit": 0.0,
        "1H_Hit": 0.0,
        "Pred_Q1_Winner": "Thunder",
        "Pred_Q2_Winner": "Thunder",
        "Pred_1H_Winner": "Thunder"
    },
    {
        "Date": "2026-04-25",
        "Home": "ATL",
        "Away": "NY",
        "Pred_Home": 128.3,
        "Pred_Away": 109.6,
        "Pred_Total": 237.9,
        "Pred_Spread": -18.7,
        "Actual_Home": 98.0,
        "Actual_Away": 114.0,
        "ML_Hit": 0.0,
        "Spread_Hit": null,
        "Total_Hit": null,
        "Q1_Hit": 0.0,
        "Q2_Hit": 0.0,
        "1H_Hit": 0.0,
        "Pred_Q1_Winner": "Hawks",
        "Pred_Q2_Winner": "Hawks",
        "Pred_1H_Winner": "Hawks"
    },
    {
        "Date": "2026-04-25",
        "Home": "MIN",
        "Away": "DEN",
        "Pred_Home": 109.1,
        "Pred_Away": 129.6,
        "Pred_Total": 238.7,
        "Pred_Spread": 20.5,
        "Actual_Home": 112.0,
        "Actual_Away": 96.0,
        "ML_Hit": 0.0,
        "Spread_Hit": null,
        "Total_Hit": null,
        "Q1_Hit": 0.0,
        "Q2_Hit": 0.0,
        "1H_Hit": 0.0,
        "Pred_Q1_Winner": "Nuggets",
        "Pred_Q2_Winner": "Nuggets",
        "Pred_1H_Winner": "Nuggets"
    },
    {
        "Date": "2026-04-26",
        "Home": "TOR",
        "Away": "CLE",
        "Pred_Home": 127.7,
        "Pred_Away": 118.5,
        "Pred_Total": 246.2,
        "Pred_Spread": -9.2,
        "Actual_Home": 93.0,
        "Actual_Away": 89.0,
        "ML_Hit": 1.0,
        "Spread_Hit": null,
        "Total_Hit": null,
        "Q1_Hit": 0.0,
        "Q2_Hit": 0.0,
        "1H_Hit": 0.0,
        "Pred_Q1_Winner": "Raptors",
        "Pred_Q2_Winner": "Cavaliers",
        "Pred_1H_Winner": "Raptors"
    },
    {
        "Date": "2026-04-26",
        "Home": "POR",
        "Away": "SA",
        "Pred_Home": 123.9,
        "Pred_Away": 111.6,
        "Pred_Total": 235.5,
        "Pred_Spread": -12.3,
        "Actual_Home": 93.0,
        "Actual_Away": 114.0,
        "ML_Hit": 0.0,
        "Spread_Hit": null,
        "Total_Hit": null,
        "Q1_Hit": 0.0,
        "Q2_Hit": 0.0,
        "1H_Hit": 0.0,
        "Pred_Q1_Winner": "Blazers",
        "Pred_Q2_Winner": "Blazers",
        "Pred_1H_Winner": "Blazers"
    },
    {
        "Date": "2026-04-26",
        "Home": "PHI",
        "Away": "BOS",
        "Pred_Home": 113.4,
        "Pred_Away": 113.7,
        "Pred_Total": 227.1,
        "Pred_Spread": 0.3,
        "Actual_Home": 96.0,
        "Actual_Away": 128.0,
        "ML_Hit": 1.0,
        "Spread_Hit": null,
        "Total_Hit": null,
        "Q1_Hit": 0.0,
        "Q2_Hit": 0.0,
        "1H_Hit": 0.0,
        "Pred_Q1_Winner": "Celtics",
        "Pred_Q2_Winner": "76ers",
        "Pred_1H_Winner": "Celtics"
    },
    {
        "Date": "2026-04-26",
        "Home": "HOU",
        "Away": "LAL",
        "Pred_Home": 128.6,
        "Pred_Away": 118.5,
        "Pred_Total": 247.1,
        "Pred_Spread": -10.1,
        "Actual_Home": 115.0,
        "Actual_Away": 96.0,
        "ML_Hit": 1.0,
        "Spread_Hit": null,
        "Total_Hit": null,
        "Q1_Hit": 0.0,
        "Q2_Hit": 0.0,
        "1H_Hit": 0.0,
        "Pred_Q1_Winner": "Rockets",
        "Pred_Q2_Winner": "Rockets",
        "Pred_1H_Winner": "Rockets"
    },
    {
        "Date": "2026-04-27",
        "Home": "ORL",
        "Away": "DET",
        "Pred_Home": 120.7,
        "Pred_Away": 117.8,
        "Pred_Total": 238.5,
        "Pred_Spread": -2.9,
        "Actual_Home": 94.0,
        "Actual_Away": 88.0,
        "ML_Hit": 1.0,
        "Spread_Hit": null,
        "Total_Hit": null,
        "Q1_Hit": 0.0,
        "Q2_Hit": 0.0,
        "1H_Hit": 0.0,
        "Pred_Q1_Winner": "Pistons",
        "Pred_Q2_Winner": "Magic",
        "Pred_1H_Winner": "Magic"
    },
    {
        "Date": "2026-04-27",
        "Home": "PHX",
        "Away": "OKC",
        "Pred_Home": 115.3,
        "Pred_Away": 125.8,
        "Pred_Total": 241.1,
        "Pred_Spread": 10.5,
        "Actual_Home": 122.0,
        "Actual_Away": 131.0,
        "ML_Hit": 1.0,
        "Spread_Hit": null,
        "Total_Hit": null,
        "Q1_Hit": 0.0,
        "Q2_Hit": 0.0,
        "1H_Hit": 0.0,
        "Pred_Q1_Winner": "Thunder",
        "Pred_Q2_Winner": "Thunder",
        "Pred_1H_Winner": "Thunder"
    },
    {
        "Date": "2026-04-27",
        "Home": "DEN",
        "Away": "MIN",
        "Pred_Home": 131.1,
        "Pred_Away": 104.1,
        "Pred_Total": 235.2,
        "Pred_Spread": -27.0,
        "Actual_Home": 125.0,
        "Actual_Away": 113.0,
        "ML_Hit": 1.0,
        "Spread_Hit": null,
        "Total_Hit": null,
        "Q1_Hit": 0.0,
        "Q2_Hit": 0.0,
        "1H_Hit": 0.0,
        "Pred_Q1_Winner": "Nuggets",
        "Pred_Q2_Winner": "Nuggets",
        "Pred_1H_Winner": "Nuggets"
    },
    {
        "Date": "2026-04-28",
        "Home": "BOS",
        "Away": "PHI",
        "Pred_Home": 122.7,
        "Pred_Away": 123.1,
        "Pred_Total": 245.8,
        "Pred_Spread": 0.4,
        "Actual_Home": 97.0,
        "Actual_Away": 113.0,
        "ML_Hit": 1.0,
        "Spread_Hit": null,
        "Total_Hit": null,
        "Q1_Hit": 0.0,
        "Q2_Hit": 0.0,
        "1H_Hit": 0.0,
        "Pred_Q1_Winner": "Celtics",
        "Pred_Q2_Winner": "76ers",
        "Pred_1H_Winner": "76ers"
    },
    {
        "Date": "2026-04-28",
        "Home": "NY",
        "Away": "ATL",
        "Pred_Home": 112.0,
        "Pred_Away": 123.5,
        "Pred_Total": 235.5,
        "Pred_Spread": 11.5,
        "Actual_Home": 126.0,
        "Actual_Away": 97.0,
        "ML_Hit": 0.0,
        "Spread_Hit": null,
        "Total_Hit": null,
        "Q1_Hit": 0.0,
        "Q2_Hit": 0.0,
        "1H_Hit": 0.0,
        "Pred_Q1_Winner": "Hawks",
        "Pred_Q2_Winner": "Hawks",
        "Pred_1H_Winner": "Hawks"
    },
    {
        "Date": "2026-04-28",
        "Home": "SA",
        "Away": "POR",
        "Pred_Home": 113.7,
        "Pred_Away": 118.8,
        "Pred_Total": 232.5,
        "Pred_Spread": 5.1,
        "Actual_Home": 114.0,
        "Actual_Away": 95.0,
        "ML_Hit": 0.0,
        "Spread_Hit": null,
        "Total_Hit": null,
        "Q1_Hit": 0.0,
        "Q2_Hit": 0.0,
        "1H_Hit": 0.0,
        "Pred_Q1_Winner": "Blazers",
        "Pred_Q2_Winner": "Blazers",
        "Pred_1H_Winner": "Blazers"
    },
    {
        "Date": "2026-04-29",
        "Home": "DET",
        "Away": "ORL",
        "Pred_Home": 124.7,
        "Pred_Away": 114.1,
        "Pred_Total": 238.8,
        "Pred_Spread": -10.6,
        "Actual_Home": 116.0,
        "Actual_Away": 109.0,
        "ML_Hit": 1.0,
        "Spread_Hit": null,
        "Total_Hit": null,
        "Q1_Hit": 0.0,
        "Q2_Hit": 0.0,
        "1H_Hit": 0.0,
        "Pred_Q1_Winner": "Pistons",
        "Pred_Q2_Winner": "Magic",
        "Pred_1H_Winner": "Pistons"
    },
    {
        "Date": "2026-04-29",
        "Home": "CLE",
        "Away": "TOR",
        "Pred_Home": 123.2,
        "Pred_Away": 120.9,
        "Pred_Total": 244.1,
        "Pred_Spread": -2.3,
        "Actual_Home": 125.0,
        "Actual_Away": 120.0,
        "ML_Hit": 1.0,
        "Spread_Hit": null,
        "Total_Hit": null,
        "Q1_Hit": 0.0,
        "Q2_Hit": 0.0,
        "1H_Hit": 0.0,
        "Pred_Q1_Winner": "Cavaliers",
        "Pred_Q2_Winner": "Cavaliers",
        "Pred_1H_Winner": "Cavaliers"
    },
    {
        "Date": "2026-04-29",
        "Home": "LAL",
        "Away": "HOU",
        "Pred_Home": 112.5,
        "Pred_Away": 113.5,
        "Pred_Total": 226.0,
        "Pred_Spread": 1.0,
        "Actual_Home": 93.0,
        "Actual_Away": 99.0,
        "ML_Hit": 1.0,
        "Spread_Hit": null,
        "Total_Hit": null,
        "Q1_Hit": 0.0,
        "Q2_Hit": 0.0,
        "1H_Hit": 0.0,
        "Pred_Q1_Winner": "Rockets",
        "Pred_Q2_Winner": "Rockets",
        "Pred_1H_Winner": "Rockets"
    },
    {
        "Date": "2026-04-30",
        "Home": "ATL",
        "Away": "NY",
        "Pred_Home": 125.0,
        "Pred_Away": 111.6,
        "Pred_Total": 236.6,
        "Pred_Spread": -13.4,
        "Actual_Home": 89.0,
        "Actual_Away": 140.0,
        "ML_Hit": 0.0,
        "Spread_Hit": null,
        "Total_Hit": null,
        "Q1_Hit": 0.0,
        "Q2_Hit": 0.0,
        "1H_Hit": 0.0,
        "Pred_Q1_Winner": "Hawks",
        "Pred_Q2_Winner": "Hawks",
        "Pred_1H_Winner": "Hawks"
    },
    {
        "Date": "2026-04-30",
        "Home": "PHI",
        "Away": "BOS",
        "Pred_Home": 116.2,
        "Pred_Away": 124.9,
        "Pred_Total": 241.1,
        "Pred_Spread": 8.7,
        "Actual_Home": 106.0,
        "Actual_Away": 93.0,
        "ML_Hit": 0.0,
        "Spread_Hit": null,
        "Total_Hit": null,
        "Q1_Hit": 0.0,
        "Q2_Hit": 0.0,
        "1H_Hit": 0.0,
        "Pred_Q1_Winner": "Celtics",
        "Pred_Q2_Winner": "76ers",
        "Pred_1H_Winner": "Celtics"
    },
    {
        "Date": "2026-04-30",
        "Home": "MIN",
        "Away": "DEN",
        "Pred_Home": 111.0,
        "Pred_Away": 129.5,
        "Pred_Total": 240.5,
        "Pred_Spread": 18.5,
        "Actual_Home": 110.0,
        "Actual_Away": 98.0,
        "ML_Hit": 0.0,
        "Spread_Hit": null,
        "Total_Hit": null,
        "Q1_Hit": 0.0,
        "Q2_Hit": 0.0,
        "1H_Hit": 0.0,
        "Pred_Q1_Winner": "Nuggets",
        "Pred_Q2_Winner": "Nuggets",
        "Pred_1H_Winner": "Nuggets"
    },
    {
        "Date": "2026-05-01",
        "Home": "ORL",
        "Away": "DET",
        "Pred_Home": 121.6,
        "Pred_Away": 118.7,
        "Pred_Total": 240.3,
        "Pred_Spread": -2.9,
        "Actual_Home": 79.0,
        "Actual_Away": 93.0,
        "ML_Hit": 0.0,
        "Spread_Hit": null,
        "Total_Hit": null,
        "Q1_Hit": 0.0,
        "Q2_Hit": 0.0,
        "1H_Hit": 0.0,
        "Pred_Q1_Winner": "Pistons",
        "Pred_Q2_Winner": "Magic",
        "Pred_1H_Winner": "Magic"
    },
    {
        "Date": "2026-05-01",
        "Home": "TOR",
        "Away": "CLE",
        "Pred_Home": 122.4,
        "Pred_Away": 122.6,
        "Pred_Total": 245.0,
        "Pred_Spread": 0.2,
        "Actual_Home": 112.0,
        "Actual_Away": 110.0,
        "ML_Hit": 0.0,
        "Spread_Hit": null,
        "Total_Hit": null,
        "Q1_Hit": 0.0,
        "Q2_Hit": 0.0,
        "1H_Hit": 0.0,
        "Pred_Q1_Winner": "Raptors",
        "Pred_Q2_Winner": "Cavaliers",
        "Pred_1H_Winner": "Cavaliers"
    },
    {
        "Date": "2026-05-01",
        "Home": "HOU",
        "Away": "LAL",
        "Pred_Home": 126.1,
        "Pred_Away": 121.5,
        "Pred_Total": 247.6,
        "Pred_Spread": -4.6,
        "Actual_Home": 78.0,
        "Actual_Away": 98.0,
        "ML_Hit": 0.0,
        "Spread_Hit": null,
        "Total_Hit": null,
        "Q1_Hit": 0.0,
        "Q2_Hit": 0.0,
        "1H_Hit": 0.0,
        "Pred_Q1_Winner": "Rockets",
        "Pred_Q2_Winner": "Rockets",
        "Pred_1H_Winner": "Rockets"
    }
]